zappend/__init__.py
zappend/api.py
zappend/cli.py
zappend/context.py
zappend/log.py
zappend/metadata.py
zappend/processor.py
zappend/profiler.py
zappend/rollbackstore.py
zappend/tailoring.py
zappend/config/__init__.py
zappend/config/attrs.py
zappend/config/config.py
zappend/config/defaults.py
zappend/config/markdown.py
zappend/config/normalize.py
zappend/config/schema.py
zappend/config/validate.py
zappend/contrib/__init__.py
zappend/contrib/levels.py
zappend/fsutil/__init__.py
zappend/fsutil/fileobj.py
zappend/fsutil/path.py
zappend/fsutil/transaction.py
zappend/slice/__init__.py
zappend/slice/callable.py
zappend/slice/cm.py
zappend/slice/source.py
zappend/slice/sources/__init__.py
zappend/slice/sources/memory.py
zappend/slice/sources/persistent.py
zappend/slice/sources/temporary.py
zappend-0.8.0.dist-info/LICENSE
zappend-0.8.0.dist-info/METADATA
zappend-0.8.0.dist-info/WHEEL
zappend-0.8.0.dist-info/entry_points.txt
zappend-0.8.0.dist-info/top_level.txt
zappend-0.8.0.dist-info/RECORD
