Metadata-Version: 2.1
Name: zappend
Version: 0.8.0
Summary: Tool for robustly creating and updating Zarr datacubes from smaller slices
Author-email: Norman Fomferra <norman.fomferra@brockmann-consult.de>
License: MIT
Project-URL: Documentation, https://bcdev.github.io/zappend/
Project-URL: Issues, https://github.com/bcdev/zappend/issues
Project-URL: Changelog, https://github.com/bcdev/zappend/blob/main/CHANGES.md
Project-URL: Repository, https://github.com/bcdev/zappend
Keywords: analysis ready data,data science,datacube,xarray,zarr
Requires-Python: >=3.10
License-File: LICENSE
Requires-Dist: click
Requires-Dist: dask
Requires-Dist: fsspec
Requires-Dist: jsonschema
Requires-Dist: numcodecs
Requires-Dist: numpy
Requires-Dist: pyyaml
Requires-Dist: xarray
Requires-Dist: zarr
Provides-Extra: dev
Requires-Dist: pytest ; extra == 'dev'
Requires-Dist: pytest-cov ; extra == 'dev'
Requires-Dist: black ; extra == 'dev'
Requires-Dist: flake8 ; extra == 'dev'
Requires-Dist: flake8-bugbear ; extra == 'dev'
Requires-Dist: h5netcdf ; extra == 'dev'
Requires-Dist: s3fs ; extra == 'dev'
Requires-Dist: scipy ; extra == 'dev'
Requires-Dist: pyproj ; extra == 'dev'
Provides-Extra: doc
Requires-Dist: mkdocs ; extra == 'doc'
Requires-Dist: mkdocs-material ; extra == 'doc'
Requires-Dist: mkdocstrings ; extra == 'doc'
Requires-Dist: mkdocstrings-python ; extra == 'doc'
